like_spider/__init__.py
like_spider/config.py
like_spider/config_example.py
like_spider/excel.py
like_spider/fireFox.py
like_spider/html.py
like_spider/mysql.py
like_spider/request.py
like_spider/doc/__init__.py
like_spider/doc/en/__init__.py
like_spider/doc/zh/__init__.py
like_spider-1.2.2.dist-info/LICENSE
like_spider-1.2.2.dist-info/METADATA
like_spider-1.2.2.dist-info/WHEEL
like_spider-1.2.2.dist-info/top_level.txt
like_spider-1.2.2.dist-info/RECORD
