Metadata-Version: 2.1
Name: like-spider
Version: 1.2.2
Summary: a crawler framework that allows developers to easily extract web page information and quickly store data
Home-page: https://github.com/wuyingjie1002/like_spider
Author: Yingjie Wu
Author-email: wyjhaha@foxmail.com
License: UNKNOWN
Platform: UNKNOWN
Requires-Dist: requests
Requires-Dist: pymysql
Requires-Dist: openpyxl
Requires-Dist: selenium
